qsck/__init__.py
qsck/format_cli.py
qsck/parse_cli.py
qsck/util.py
qsck-0.3.dist-info/LICENSE
qsck-0.3.dist-info/METADATA
qsck-0.3.dist-info/WHEEL
qsck-0.3.dist-info/entry_points.txt
qsck-0.3.dist-info/top_level.txt
qsck-0.3.dist-info/RECORD
