Metadata-Version: 2.1
Name: qsck
Version: 0.3
Summary: The shitty ".qs" file (de-)serializer
Home-page: https://github.com/mblomdahl/qsck
Author: Mats Blomdahl
Author-email: mats.blomdahl@gmail.com
License: The Unlicense
Platform: UNKNOWN
Classifier: Development Status :: 3 - Alpha
Classifier: Environment :: Console
Classifier: Intended Audience :: Developers
Classifier: License :: OSI Approved
Classifier: Natural Language :: English
Classifier: Operating System :: POSIX
Classifier: Programming Language :: Python :: 3.6
Classifier: Programming Language :: Python :: 3.7
Classifier: Topic :: Software Development :: Quality Assurance
Requires-Python: >=3.6
Requires-Dist: Click
Requires-Dist: ujson
